staxapp/__init__.py
staxapp/api.py
staxapp/auth.py
staxapp/aws_srp.py
staxapp/config.py
staxapp/contract.py
staxapp/exceptions.py
staxapp/openapi.py
staxapp/retry.py
staxapp/data/schema.json
staxapp-1.3.1.dist-info/LICENSE.md
staxapp-1.3.1.dist-info/METADATA
staxapp-1.3.1.dist-info/WHEEL
staxapp-1.3.1.dist-info/top_level.txt
staxapp-1.3.1.dist-info/RECORD
