Metadata-Version: 2.1
Name: staxapp
Version: 1.3.1
Summary: Stax Python SDK
Home-page: https://stax.io
Author: Stax
Author-email: support@stax.io
License: Apache License 2.0
Project-URL: GitHub, https://github.com/stax-labs/lib-stax-python-sdk
Classifier: Development Status :: 4 - Beta
Classifier: Intended Audience :: Developers
Classifier: Natural Language :: English
Classifier: License :: OSI Approved :: Apache Software License
Classifier: Programming Language :: Python
Classifier: Programming Language :: Python :: 3
Classifier: Programming Language :: Python :: 3.6
Classifier: Programming Language :: Python :: 3.7
Classifier: Programming Language :: Python :: 3.8
Classifier: Programming Language :: Python :: 3.9
Requires-Python: >=3.6
License-File: LICENSE.md
Requires-Dist: boto3
Requires-Dist: prance
Requires-Dist: requests
Requires-Dist: aws-requests-auth
Requires-Dist: openapi-spec-validator (==0.2.9)
